jwtauthenticatortest1/__init__.py
jwtauthenticatortest1/jwtauthenticatortest1.py
jwtauthenticatortest1-1.0.1.dist-info/LICENSE
jwtauthenticatortest1-1.0.1.dist-info/METADATA
jwtauthenticatortest1-1.0.1.dist-info/WHEEL
jwtauthenticatortest1-1.0.1.dist-info/top_level.txt
jwtauthenticatortest1-1.0.1.dist-info/RECORD
